{
  "id": 1307390,
  "name": "Foley v. Brown, Appellant",
  "name_abbreviation": "Foley v. Brown",
  "decision_date": "1962-04-17",
  "docket_number": "Appeals, Nos. 131, 132, 133 and 134",
  "first_page": "29",
  "last_page": "29",
  "citations": [
    {
      "type": "official",
      "cite": "407 Pa. 29"
    }
  ],
  "court": {
    "name_abbreviation": "Pa.",
    "id": 8832,
    "name": "Supreme Court of Pennsylvania"
  },
  "jurisdiction": {
    "id": 6,
    "name_long": "Pennsylvania",
    "name": "Pa."
  },
  "cites_to": [],
  "analysis": {
    "cardinality": 47,
    "char_count": 360,
    "ocr_confidence": 0.42,
    "sha256": "a1fd7637f65f8d7f8f14a3d91de987ddff83f198d7edf4ad5c915015e9cde7ba",
    "simhash": "1:4356109e2af0c0eb",
    "word_count": 58
  },
  "last_updated": "2023-07-14T16:51:13.554543+00:00",
  "provenance": {
    "date_added": "2019-08-29",
    "source": "Harvard",
    "batch": "2018"
  },
  "casebody": {
    "judges": [
      "Before Bell, C. J., Musmanno, Jones, Cohen, Eagen and O\u2019Brien, JJ."
    ],
    "parties": [
      "Foley v. Brown, Appellant."
    ],
    "opinions": [
      {
        "text": "Opinion\nPer Curiam,\nJudgments affirmed.",
        "type": "majority",
        "author": "Per Curiam,"
      }
    ],
    "attorneys": [
      "B. Fred Mercer, with him Mercer and Buchley, for appellants.",
      "John E. Evans, Jr., with him Thomas P. Mulvaney, and Evans, Ivory \u00e9 Evans, for appellees.",
      "William J. Lancaster, for appellee."
    ],
    "corrections": "",
    "head_matter": "Foley v. Brown, Appellant.\nArgued March 19, 1962.\nApril 17, 1962:\nBefore Bell, C. J., Musmanno, Jones, Cohen, Eagen and O\u2019Brien, JJ.\nB. Fred Mercer, with him Mercer and Buchley, for appellants.\nJohn E. Evans, Jr., with him Thomas P. Mulvaney, and Evans, Ivory \u00e9 Evans, for appellees.\nWilliam J. Lancaster, for appellee."
  },
  "file_name": "0029-01",
  "first_page_order": 51,
  "last_page_order": 51
}
